.gitignore
101903131-data.csv
101903131.py
LICENSE.txt
README.md
output.csv
setup.cfg
setup.py
topsis.py
Topsis_Shubham_101903131.egg-info/PKG-INFO
Topsis_Shubham_101903131.egg-info/SOURCES.txt
Topsis_Shubham_101903131.egg-info/dependency_links.txt
Topsis_Shubham_101903131.egg-info/entry_points.txt
Topsis_Shubham_101903131.egg-info/requires.txt
Topsis_Shubham_101903131.egg-info/top_level.txt
dist/Topsis-Shubham-101903131-1.0.0.tar.gz
dist/Topsis-Shubham-101903131-1.1.0.tar.gz
dist/Topsis-Shubham-101903131-1.1.1.tar.gz
dist/Topsis-Shubham-101903131-1.1.2.tar.gz
topsis_py/topsis.py