Metadata-Version: 2.1
Name: Topsis-Shubham-101903131
Version: 1.1.3
Summary: A Python package implementing TOPSIS technique.
Home-page: UNKNOWN
Author: Shubham Trivedi
Author-email: strivedi_be19@thapar.edu
License: MIT
Platform: UNKNOWN
Classifier: License :: OSI Approved :: MIT License
Classifier: Programming Language :: Python :: 3
Classifier: Programming Language :: Python :: 3.7
